mediocreatbest/__init__.py
mediocreatbest/_auto.py
mediocreatbest/_config.py
mediocreatbest/_contextgenerator.py
mediocreatbest/_doctest.py
mediocreatbest/_embed.py
mediocreatbest/_getkey.py
mediocreatbest/_grid.py
mediocreatbest/_llm.py
mediocreatbest/_module.py
mediocreatbest/_random.py
mediocreatbest/_run.py
mediocreatbest/_scope.py
mediocreatbest/_singledispatch.py
mediocreatbest/_source.py
mediocreatbest/_sqlquery.py
mediocreatbest/_stuple.py
mediocreatbest/_textarea.py
mediocreatbest/_track.py
mediocreatbest/_verbatim.py
mediocreatbest/_wrap.py
mediocreatbest/cli/__init__.py
mediocreatbest/cli/aider_update_model_metadata.py
mediocreatbest/cli/decrypt.py
mediocreatbest/cli/encrypt.py
mediocreatbest-0.3.17.dist-info/METADATA
mediocreatbest-0.3.17.dist-info/WHEEL
mediocreatbest-0.3.17.dist-info/entry_points.txt
mediocreatbest-0.3.17.dist-info/top_level.txt
mediocreatbest-0.3.17.dist-info/RECORD
