Metadata-Version: 2.2
Name: mediocreatbest
Version: 0.3.17
Summary: A mediocre at best utility library for Python
Author: https://github.com/player1537
License: wtfpl
Project-URL: Homepage, https://github.com/player1537/mediocreatbest
Project-URL: Issues, https://github.com/player1537/mediocreatbest/issues
Classifier: Development Status :: 4 - Beta
Classifier: Programming Language :: Python :: 3
Classifier: License :: OSI Approved :: MIT License
Classifier: Operating System :: OS Independent
Requires-Dist: requests
Requires-Dist: pandas
Requires-Dist: tqdm
Provides-Extra: dev
Requires-Dist: pytest==8.3.4; extra == "dev"
